CHANGELOG.md
LICENSE
escapyde/__init__.py
escapyde/ansi.py
escapyde/colours.py
escapyde/config.py
escapyde/examples/__init__.py
escapyde/examples/text.py
escapyde/py.typed
escapyde/validators.py
escapyde-1.0.2.dist-info/LICENSE
escapyde-1.0.2.dist-info/METADATA
escapyde-1.0.2.dist-info/WHEEL
escapyde-1.0.2.dist-info/RECORD
